{"schema":1,"succeeded":true,"raw-packets":[{"dst-ts":16900748152015087827,"ip-ttl":255,"src-ts":16900748151945991385,"seq-num":0,"dst-clock-err":0.000222206,"src-clock-err":0.000436783,"dst-clock-sync":true,"src-clock-sync":true},{"dst-ts":16900748152873325372,"ip-ttl":255,"src-ts":16900748152772244309,"seq-num":1,"dst-clock-err":0.000222206,"src-clock-err":0.000436783,"dst-clock-sync":true,"src-clock-sync":true},{"dst-ts":16900748152984844198,"ip-ttl":255,"src-ts":16900748152914699784,"seq-num":2,"dst-clock-err":0.000222206,"src-clock-err":0.000436783,"dst-clock-sync":true,"src-clock-sync":true},{"dst-ts":16900748153219207678,"ip-ttl":255,"src-ts":16900748153113251827,"seq-num":3,"dst-clock-err":0.000222206,"src-clock-err":0.000436783,"dst-clock-sync":true,"src-clock-sync":true},{"dst-ts":16900748153646707248,"ip-ttl":255,"src-ts":16900748153585663870,"seq-num":4,"dst-clock-err":0.000222206,"src-clock-err":0.000436783,"dst-clock-sync":true,"src-clock-sync":true},{"dst-ts":16900748153990334697,"ip-ttl":255,"src-ts":16900748153857840243,"seq-num":5,"dst-clock-err":0.000222206,"src-clock-err":0.000436783,"dst-clock-sync":true,"src-clock-sync":true},{"dst-ts":16900748154162288007,"ip-ttl":255,"src-ts":16900748154049181036,"seq-num":6,"dst-clock-err":0.000222206,"src-clock-err":0.000436783,"dst-clock-sync":true,"src-clock-sync":true},{"dst-ts":16900748154935648043,"ip-ttl":255,"src-ts":16900748154823109489,"seq-num":7,"dst-clock-err":0.000222206,"src-clock-err":0.000436783,"dst-clock-sync":true,"src-clock-sync":true},{"dst-ts":16900748155365333752,"ip-ttl":255,"src-ts":16900748155300782867,"seq-num":8,"dst-clock-err":0.000222206,"src-clock-err":0.000436783,"dst-clock-sync":true,"src-clock-sync":true},{"dst-ts":16900748156138479404,"ip-ttl":255,"src-ts":16900748156046573873,"seq-num":9,"dst-clock-err":0.000222206,"src-clock-err":0.000436783,"dst-clock-sync":true,"src-clock-sync":true},{"dst-ts":16900748157168790519,"ip-ttl":255,"src-ts":16900748157116514651,"seq-num":10,"dst-clock-err":0.000222206,"src-clock-err":0.000436783,"dst-clock-sync":true,"src-clock-sync":true},{"dst-ts":16900748157770012926,"ip-ttl":255,"src-ts":16900748157714580257,"seq-num":11,"dst-clock-err":0.000222206,"src-clock-err":0.000436783,"dst-clock-sync":true,"src-clock-sync":true},{"dst-ts":16900748158800637213,"ip-ttl":255,"src-ts":16900748158679570331,"seq-num":12,"dst-clock-err":0.000222206,"src-clock-err":0.000436783,"dst-clock-sync":true,"src-clock-sync":true},{"dst-ts":16900748159659437398,"ip-ttl":255,"src-ts":16900748159555619105,"seq-num":13,"dst-clock-err":0.000222206,"src-clock-err":0.000436783,"dst-clock-sync":true,"src-clock-sync":true},{"dst-ts":16900748161205509661,"ip-ttl":255,"src-ts":16900748161149202296,"seq-num":14,"dst-clock-err":0.000222206,"src-clock-err":0.000436783,"dst-clock-sync":true,"src-clock-sync":true},{"dst-ts":16900748162066319891,"ip-ttl":255,"src-ts":16900748161976881149,"seq-num":15,"dst-clock-err":0.000222206,"src-clock-err":0.000436783,"dst-clock-sync":true,"src-clock-sync":true},{"dst-ts":16900748162666730549,"ip-ttl":255,"src-ts":16900748162569200088,"seq-num":16,"dst-clock-err":0.000222206,"src-clock-err":0.000436783,"dst-clock-sync":true,"src-clock-sync":true},{"dst-ts":16900748163354118230,"ip-ttl":255,"src-ts":16900748163262043850,"seq-num":17,"dst-clock-err":0.000222206,"src-clock-err":0.000436783,"dst-clock-sync":true,"src-clock-sync":true},{"dst-ts":16900748163697470800,"ip-ttl":255,"src-ts":16900748163559483220,"seq-num":18,"dst-clock-err":0.000222206,"src-clock-err":0.000436783,"dst-clock-sync":true,"src-clock-sync":true},{"dst-ts":16900748163697659779,"ip-ttl":255,"src-ts":16900748163666586820,"seq-num":19,"dst-clock-err":0.000222206,"src-clock-err":0.000436783,"dst-clock-sync":true,"src-clock-sync":true},{"dst-ts":16900748164040398169,"ip-ttl":255,"src-ts":16900748163919693538,"seq-num":20,"dst-clock-err":0.000222206,"src-clock-err":0.000436783,"dst-clock-sync":true,"src-clock-sync":true},{"dst-ts":16900748164040758946,"ip-ttl":255,"src-ts":16900748163992317140,"seq-num":21,"dst-clock-err":0.000222206,"src-clock-err":0.000436783,"dst-clock-sync":true,"src-clock-sync":true},{"dst-ts":16900748164556086302,"ip-ttl":255,"src-ts":16900748164467314753,"seq-num":22,"dst-clock-err":0.000222206,"src-clock-err":0.000436783,"dst-clock-sync":true,"src-clock-sync":true},{"dst-ts":16900748164556275281,"ip-ttl":255,"src-ts":16900748164501760390,"seq-num":23,"dst-clock-err":0.000222206,"src-clock-err":0.000436783,"dst-clock-sync":true,"src-clock-sync":true},{"dst-ts":16900748165329519718,"ip-ttl":255,"src-ts":16900748165259293837,"seq-num":24,"dst-clock-err":0.000222206,"src-clock-err":0.000436783,"dst-clock-sync":true,"src-clock-sync":true},{"dst-ts":16900748165673190116,"ip-ttl":255,"src-ts":16900748165588103648,"seq-num":25,"dst-clock-err":0.000222206,"src-clock-err":0.000436783,"dst-clock-sync":true,"src-clock-sync":true},{"dst-ts":16900748165930961168,"ip-ttl":255,"src-ts":16900748165817381888,"seq-num":26,"dst-clock-err":0.000222206,"src-clock-err":0.000436783,"dst-clock-sync":true,"src-clock-sync":true},{"dst-ts":16900748166789254548,"ip-ttl":255,"src-ts":16900748166703781533,"seq-num":27,"dst-clock-err":0.000222206,"src-clock-err":0.000436783,"dst-clock-sync":true,"src-clock-sync":true},{"dst-ts":16900748167047244643,"ip-ttl":255,"src-ts":16900748166919032409,"seq-num":28,"dst-clock-err":0.000222206,"src-clock-err":0.000436783,"dst-clock-sync":true,"src-clock-sync":true},{"dst-ts":16900748167132783212,"ip-ttl":255,"src-ts":16900748167081798785,"seq-num":29,"dst-clock-err":0.000222206,"src-clock-err":0.000436783,"dst-clock-sync":true,"src-clock-sync":true},{"dst-ts":16900748167734705333,"ip-ttl":255,"src-ts":16900748167598810885,"seq-num":30,"dst-clock-err":0.000222206,"src-clock-err":0.000436783,"dst-clock-sync":true,"src-clock-sync":true},{"dst-ts":16900748167735405413,"ip-ttl":255,"src-ts":16900748167645041913,"seq-num":31,"dst-clock-err":0.000222206,"src-clock-err":0.000436783,"dst-clock-sync":true,"src-clock-sync":true},{"dst-ts":16900748167905503298,"ip-ttl":255,"src-ts":16900748167805866963,"seq-num":32,"dst-clock-err":0.000222206,"src-clock-err":0.000436783,"dst-clock-sync":true,"src-clock-sync":true},{"dst-ts":16900748169021610679,"ip-ttl":255,"src-ts":16900748168900173090,"seq-num":33,"dst-clock-err":0.000222206,"src-clock-err":0.000436783,"dst-clock-sync":true,"src-clock-sync":true},{"dst-ts":16900748169194264070,"ip-ttl":255,"src-ts":16900748169128102710,"seq-num":34,"dst-clock-err":0.000222206,"src-clock-err":0.000436783,"dst-clock-sync":true,"src-clock-sync":true},{"dst-ts":16900748169305589622,"ip-ttl":255,"src-ts":16900748169231422443,"seq-num":35,"dst-clock-err":0.000222206,"src-clock-err":0.000436783,"dst-clock-sync":true,"src-clock-sync":true},{"dst-ts":16900748169413685359,"ip-ttl":255,"src-ts":16900748169350393037,"seq-num":36,"dst-clock-err":0.000222206,"src-clock-err":0.000436783,"dst-clock-sync":true,"src-clock-sync":true},{"dst-ts":16900748170655399059,"ip-ttl":255,"src-ts":16900748170571649808,"seq-num":37,"dst-clock-err":0.000222206,"src-clock-err":0.000436783,"dst-clock-sync":true,"src-clock-sync":true},{"dst-ts":16900748171686122130,"ip-ttl":255,"src-ts":16900748171605552628,"seq-num":38,"dst-clock-err":0.000222206,"src-clock-err":0.000436783,"dst-clock-sync":true,"src-clock-sync":true},{"dst-ts":16900748171686547331,"ip-ttl":255,"src-ts":16900748171656864602,"seq-num":39,"dst-clock-err":0.000222206,"src-clock-err":0.000436783,"dst-clock-sync":true,"src-clock-sync":true},{"dst-ts":16900748172372505148,"ip-ttl":255,"src-ts":16900748172248358908,"seq-num":40,"dst-clock-err":0.000222206,"src-clock-err":0.000436783,"dst-clock-sync":true,"src-clock-sync":true},{"dst-ts":16900748172973611591,"ip-ttl":255,"src-ts":16900748172863909326,"seq-num":41,"dst-clock-err":0.000222206,"src-clock-err":0.000436783,"dst-clock-sync":true,"src-clock-sync":true},{"dst-ts":16900748173661197200,"ip-ttl":255,"src-ts":16900748173545726794,"seq-num":42,"dst-clock-err":0.000222206,"src-clock-err":0.000436783,"dst-clock-sync":true,"src-clock-sync":true},{"dst-ts":16900748173833485519,"ip-ttl":255,"src-ts":16900748173736672450,"seq-num":43,"dst-clock-err":0.000222206,"src-clock-err":0.000436783,"dst-clock-sync":true,"src-clock-sync":true},{"dst-ts":16900748174090938743,"ip-ttl":255,"src-ts":16900748173973501242,"seq-num":44,"dst-clock-err":0.000222206,"src-clock-err":0.000436783,"dst-clock-sync":true,"src-clock-sync":true},{"dst-ts":16900748175722914647,"ip-ttl":255,"src-ts":16900748175631526122,"seq-num":45,"dst-clock-err":0.000222206,"src-clock-err":0.000436783,"dst-clock-sync":true,"src-clock-sync":true},{"dst-ts":16900748175799880460,"ip-ttl":255,"src-ts":16900748175716437625,"seq-num":46,"dst-clock-err":0.000222206,"src-clock-err":0.000436783,"dst-clock-sync":true,"src-clock-sync":true},{"dst-ts":16900748175980539309,"ip-ttl":255,"src-ts":16900748175856772499,"seq-num":47,"dst-clock-err":0.000222206,"src-clock-err":0.000436783,"dst-clock-sync":true,"src-clock-sync":true},{"dst-ts":16900748176410121938,"ip-ttl":255,"src-ts":16900748176360507739,"seq-num":48,"dst-clock-err":0.000222206,"src-clock-err":0.000436783,"dst-clock-sync":true,"src-clock-sync":true},{"dst-ts":16900748176410310917,"ip-ttl":255,"src-ts":16900748176369316716,"seq-num":49,"dst-clock-err":0.000222206,"src-clock-err":0.000436783,"dst-clock-sync":true,"src-clock-sync":true},{"dst-ts":16900748176487328270,"ip-ttl":255,"src-ts":16900748176419726748,"seq-num":50,"dst-clock-err":0.000222206,"src-clock-err":0.000436783,"dst-clock-sync":true,"src-clock-sync":true},{"dst-ts":16900748177269562074,"ip-ttl":255,"src-ts":16900748177191184478,"seq-num":51,"dst-clock-err":0.000222206,"src-clock-err":0.000436783,"dst-clock-sync":true,"src-clock-sync":true},{"dst-ts":16900748177269703808,"ip-ttl":255,"src-ts":16900748177199383571,"seq-num":52,"dst-clock-err":0.000222206,"src-clock-err":0.000436783,"dst-clock-sync":true,"src-clock-sync":true},{"dst-ts":16900748177527109788,"ip-ttl":255,"src-ts":16900748177439326214,"seq-num":53,"dst-clock-err":0.000222206,"src-clock-err":0.000436783,"dst-clock-sync":true,"src-clock-sync":true},{"dst-ts":16900748177527496335,"ip-ttl":255,"src-ts":16900748177503772198,"seq-num":54,"dst-clock-err":0.000222206,"src-clock-err":0.000436783,"dst-clock-sync":true,"src-clock-sync":true},{"dst-ts":16900748177604290350,"ip-ttl":255,"src-ts":16900748177532170522,"seq-num":55,"dst-clock-err":0.000222206,"src-clock-err":0.000436783,"dst-clock-sync":true,"src-clock-sync":true},{"dst-ts":16900748177638207707,"ip-ttl":255,"src-ts":16900748177577675700,"seq-num":56,"dst-clock-err":0.000222206,"src-clock-err":0.000436783,"dst-clock-sync":true,"src-clock-sync":true},{"dst-ts":16900748178042746381,"ip-ttl":255,"src-ts":16900748177985280982,"seq-num":57,"dst-clock-err":0.000222206,"src-clock-err":0.000436783,"dst-clock-sync":true,"src-clock-sync":true},{"dst-ts":16900748178042870935,"ip-ttl":255,"src-ts":16900748178007610517,"seq-num":58,"dst-clock-err":0.000222206,"src-clock-err":0.000436783,"dst-clock-sync":true,"src-clock-sync":true},{"dst-ts":16900748178986677114,"ip-ttl":255,"src-ts":16900748178895109674,"seq-num":59,"dst-clock-err":0.000222206,"src-clock-err":0.000436783,"dst-clock-sync":true,"src-clock-sync":true}],"packets-lost":0,"packets-sent":60,"histogram-ttl":{"255":60},"max-clock-error":0.66,"packets-received":60,"histogram-latency":{"5.52":1,"6.91":1,"7.23":1,"8.21":1,"9.54":1,"11.28":1,"11.55":1,"11.87":1,"12.17":1,"12.69":1,"12.91":1,"13.11":1,"13.38":1,"14.09":1,"14.21":1,"14.74":1,"15.03":1,"15.40":1,"15.74":1,"16.09":1,"16.33":1,"16.35":1,"16.37":1,"16.79":1,"17.27":1,"18.25":1,"18.76":1,"19.43":1,"19.50":1,"19.81":1,"19.90":1,"20.44":1,"20.67":1,"20.82":1,"21.04":1,"21.28":1,"21.32":1,"21.40":1,"21.44":1,"22.54":1,"22.71":1,"23.20":1,"23.53":1,"24.17":1,"24.67":1,"25.54":1,"26.20":1,"26.33":1,"26.44":1,"26.89":1,"27.34":1,"28.10":1,"28.19":1,"28.27":1,"28.82":1,"28.90":1,"29.85":1,"30.85":1,"31.64":1,"32.13":1},"packets-reordered":0,"packets-duplicated":0}
