{"schema":1,"succeeded":true,"raw-packets":[{"dst-ts":16870463794658174349,"ip-ttl":255,"src-ts":16870463794653784893,"seq-num":0,"dst-clock-err":1.00583e-06,"src-clock-err":1.00583e-06,"dst-clock-sync":true,"src-clock-sync":true},{"dst-ts":16870463795343689785,"ip-ttl":255,"src-ts":16870463795340021883,"seq-num":1,"dst-clock-err":1.00583e-06,"src-clock-err":1.00583e-06,"dst-clock-sync":true,"src-clock-sync":true},{"dst-ts":16870463795712374072,"ip-ttl":255,"src-ts":16870463795708783480,"seq-num":2,"dst-clock-err":1.00583e-06,"src-clock-err":1.00583e-06,"dst-clock-sync":true,"src-clock-sync":true},{"dst-ts":16870463796442488448,"ip-ttl":255,"src-ts":16870463796439559280,"seq-num":3,"dst-clock-err":1.00583e-06,"src-clock-err":1.00583e-06,"dst-clock-sync":true,"src-clock-sync":true},{"dst-ts":16870463797252862877,"ip-ttl":255,"src-ts":16870463797249955184,"seq-num":4,"dst-clock-err":1.00583e-06,"src-clock-err":1.00583e-06,"dst-clock-sync":true,"src-clock-sync":true},{"dst-ts":16870463797302624368,"ip-ttl":255,"src-ts":16870463797298831912,"seq-num":5,"dst-clock-err":1.00583e-06,"src-clock-err":1.00583e-06,"dst-clock-sync":true,"src-clock-sync":true},{"dst-ts":16870463798655590606,"ip-ttl":255,"src-ts":16870463798652919137,"seq-num":6,"dst-clock-err":1.00583e-06,"src-clock-err":1.00583e-06,"dst-clock-sync":true,"src-clock-sync":true},{"dst-ts":16870463798906164152,"ip-ttl":255,"src-ts":16870463798903131905,"seq-num":7,"dst-clock-err":1.00583e-06,"src-clock-err":1.00583e-06,"dst-clock-sync":true,"src-clock-sync":true},{"dst-ts":16870463799266464664,"ip-ttl":255,"src-ts":16870463799263483956,"seq-num":8,"dst-clock-err":1.00583e-06,"src-clock-err":1.00583e-06,"dst-clock-sync":true,"src-clock-sync":true},{"dst-ts":16870463799886129660,"ip-ttl":255,"src-ts":16870463799882362974,"seq-num":9,"dst-clock-err":1.00583e-06,"src-clock-err":1.00583e-06,"dst-clock-sync":true,"src-clock-sync":true},{"dst-ts":16870463799891708823,"ip-ttl":255,"src-ts":16870463799888998698,"seq-num":10,"dst-clock-err":1.00583e-06,"src-clock-err":1.00583e-06,"dst-clock-sync":true,"src-clock-sync":true},{"dst-ts":16870463800448315109,"ip-ttl":255,"src-ts":16870463800444479704,"seq-num":11,"dst-clock-err":1.00583e-06,"src-clock-err":1.00583e-06,"dst-clock-sync":true,"src-clock-sync":true},{"dst-ts":16870463800621110234,"ip-ttl":255,"src-ts":16870463800617511051,"seq-num":12,"dst-clock-err":1.00583e-06,"src-clock-err":1.00583e-06,"dst-clock-sync":true,"src-clock-sync":true},{"dst-ts":16870463800768711080,"ip-ttl":255,"src-ts":16870463800765408250,"seq-num":13,"dst-clock-err":1.00583e-06,"src-clock-err":1.00583e-06,"dst-clock-sync":true,"src-clock-sync":true},{"dst-ts":16870463801257005912,"ip-ttl":255,"src-ts":16870463801253226340,"seq-num":14,"dst-clock-err":1.00583e-06,"src-clock-err":1.00583e-06,"dst-clock-sync":true,"src-clock-sync":true},{"dst-ts":16870463801730315603,"ip-ttl":255,"src-ts":16870463801727545349,"seq-num":15,"dst-clock-err":1.00583e-06,"src-clock-err":1.00583e-06,"dst-clock-sync":true,"src-clock-sync":true},{"dst-ts":16870463802302873398,"ip-ttl":255,"src-ts":16870463802299815381,"seq-num":16,"dst-clock-err":1.00583e-06,"src-clock-err":1.00583e-06,"dst-clock-sync":true,"src-clock-sync":true},{"dst-ts":16870463802439839905,"ip-ttl":255,"src-ts":16870463802436854903,"seq-num":17,"dst-clock-err":1.00583e-06,"src-clock-err":1.00583e-06,"dst-clock-sync":true,"src-clock-sync":true},{"dst-ts":16870463802803009455,"ip-ttl":255,"src-ts":16870463802799457517,"seq-num":18,"dst-clock-err":1.00583e-06,"src-clock-err":1.00583e-06,"dst-clock-sync":true,"src-clock-sync":true},{"dst-ts":16870463803736658701,"ip-ttl":255,"src-ts":16870463803733072403,"seq-num":19,"dst-clock-err":1.00583e-06,"src-clock-err":1.00583e-06,"dst-clock-sync":true,"src-clock-sync":true},{"dst-ts":16870463803877804211,"ip-ttl":255,"src-ts":16870463803874943763,"seq-num":20,"dst-clock-err":1.00583e-06,"src-clock-err":1.00583e-06,"dst-clock-sync":true,"src-clock-sync":true},{"dst-ts":16870463804431232222,"ip-ttl":255,"src-ts":16870463804428663832,"seq-num":21,"dst-clock-err":1.00583e-06,"src-clock-err":1.00583e-06,"dst-clock-sync":true,"src-clock-sync":true},{"dst-ts":16870463804464505334,"ip-ttl":255,"src-ts":16870463804461211094,"seq-num":22,"dst-clock-err":1.00583e-06,"src-clock-err":1.00583e-06,"dst-clock-sync":true,"src-clock-sync":true},{"dst-ts":16870463804526902619,"ip-ttl":255,"src-ts":16870463804523161702,"seq-num":23,"dst-clock-err":1.00583e-06,"src-clock-err":1.00583e-06,"dst-clock-sync":true,"src-clock-sync":true},{"dst-ts":16870463804903635675,"ip-ttl":255,"src-ts":16870463804900019313,"seq-num":24,"dst-clock-err":1.00583e-06,"src-clock-err":1.00583e-06,"dst-clock-sync":true,"src-clock-sync":true},{"dst-ts":16870463805067273929,"ip-ttl":255,"src-ts":16870463805064211617,"seq-num":25,"dst-clock-err":1.00583e-06,"src-clock-err":1.00583e-06,"dst-clock-sync":true,"src-clock-sync":true},{"dst-ts":16870463807429231532,"ip-ttl":255,"src-ts":16870463807426422624,"seq-num":26,"dst-clock-err":1.00583e-06,"src-clock-err":1.00583e-06,"dst-clock-sync":true,"src-clock-sync":true},{"dst-ts":16870463807628410641,"ip-ttl":255,"src-ts":16870463807624884472,"seq-num":27,"dst-clock-err":1.00583e-06,"src-clock-err":1.00583e-06,"dst-clock-sync":true,"src-clock-sync":true},{"dst-ts":16870463807691898847,"ip-ttl":255,"src-ts":16870463807689016924,"seq-num":28,"dst-clock-err":1.00583e-06,"src-clock-err":1.00583e-06,"dst-clock-sync":true,"src-clock-sync":true},{"dst-ts":16870463807886722859,"ip-ttl":255,"src-ts":16870463807883312655,"seq-num":29,"dst-clock-err":1.00583e-06,"src-clock-err":1.00583e-06,"dst-clock-sync":true,"src-clock-sync":true},{"dst-ts":16870463808171586565,"ip-ttl":255,"src-ts":16870463808168708936,"seq-num":30,"dst-clock-err":1.00583e-06,"src-clock-err":1.00583e-06,"dst-clock-sync":true,"src-clock-sync":true},{"dst-ts":16870463809839837762,"ip-ttl":255,"src-ts":16870463809837239306,"seq-num":31,"dst-clock-err":1.00583e-06,"src-clock-err":1.00583e-06,"dst-clock-sync":true,"src-clock-sync":true},{"dst-ts":16870463809996449449,"ip-ttl":255,"src-ts":16870463809992914691,"seq-num":32,"dst-clock-err":1.00583e-06,"src-clock-err":1.00583e-06,"dst-clock-sync":true,"src-clock-sync":true},{"dst-ts":16870463810211081850,"ip-ttl":255,"src-ts":16870463810207538502,"seq-num":33,"dst-clock-err":1.00583e-06,"src-clock-err":1.00583e-06,"dst-clock-sync":true,"src-clock-sync":true},{"dst-ts":16870463810506816118,"ip-ttl":255,"src-ts":16870463810503560533,"seq-num":34,"dst-clock-err":1.00583e-06,"src-clock-err":1.00583e-06,"dst-clock-sync":true,"src-clock-sync":true},{"dst-ts":16870463810972446407,"ip-ttl":255,"src-ts":16870463810969061973,"seq-num":35,"dst-clock-err":1.00583e-06,"src-clock-err":1.00583e-06,"dst-clock-sync":true,"src-clock-sync":true},{"dst-ts":16870463811114158853,"ip-ttl":255,"src-ts":16870463811111431549,"seq-num":36,"dst-clock-err":1.00583e-06,"src-clock-err":1.00583e-06,"dst-clock-sync":true,"src-clock-sync":true},{"dst-ts":16870463811145756928,"ip-ttl":255,"src-ts":16870463811142879300,"seq-num":37,"dst-clock-err":1.00583e-06,"src-clock-err":1.00583e-06,"dst-clock-sync":true,"src-clock-sync":true},{"dst-ts":16870463811292009154,"ip-ttl":255,"src-ts":16870463811288976907,"seq-num":38,"dst-clock-err":1.00583e-06,"src-clock-err":1.00583e-06,"dst-clock-sync":true,"src-clock-sync":true},{"dst-ts":16870463811776786683,"ip-ttl":255,"src-ts":16870463811773904760,"seq-num":39,"dst-clock-err":1.00583e-06,"src-clock-err":1.00583e-06,"dst-clock-sync":true,"src-clock-sync":true},{"dst-ts":16870463812646362941,"ip-ttl":255,"src-ts":16870463812643652817,"seq-num":40,"dst-clock-err":1.00583e-06,"src-clock-err":1.00583e-06,"dst-clock-sync":true,"src-clock-sync":true},{"dst-ts":16870463812712054466,"ip-ttl":255,"src-ts":16870463812709168248,"seq-num":41,"dst-clock-err":1.00583e-06,"src-clock-err":1.00583e-06,"dst-clock-sync":true,"src-clock-sync":true},{"dst-ts":16870463812983294536,"ip-ttl":255,"src-ts":16870463812979978821,"seq-num":42,"dst-clock-err":1.00583e-06,"src-clock-err":1.00583e-06,"dst-clock-sync":true,"src-clock-sync":true},{"dst-ts":16870463813625259002,"ip-ttl":255,"src-ts":16870463813621732834,"seq-num":43,"dst-clock-err":1.00583e-06,"src-clock-err":1.00583e-06,"dst-clock-sync":true,"src-clock-sync":true},{"dst-ts":16870463813835690925,"ip-ttl":255,"src-ts":16870463813832684448,"seq-num":44,"dst-clock-err":1.00583e-06,"src-clock-err":1.00583e-06,"dst-clock-sync":true,"src-clock-sync":true},{"dst-ts":16870463814357065595,"ip-ttl":255,"src-ts":16870463814354368356,"seq-num":45,"dst-clock-err":1.00583e-06,"src-clock-err":1.00583e-06,"dst-clock-sync":true,"src-clock-sync":true},{"dst-ts":16870463815058077272,"ip-ttl":255,"src-ts":16870463815054624119,"seq-num":46,"dst-clock-err":1.00583e-06,"src-clock-err":1.00583e-06,"dst-clock-sync":true,"src-clock-sync":true},{"dst-ts":16870463815406442070,"ip-ttl":255,"src-ts":16870463815403414118,"seq-num":47,"dst-clock-err":1.00583e-06,"src-clock-err":1.00583e-06,"dst-clock-sync":true,"src-clock-sync":true},{"dst-ts":16870463816087731343,"ip-ttl":255,"src-ts":16870463816084772110,"seq-num":48,"dst-clock-err":1.00583e-06,"src-clock-err":1.00583e-06,"dst-clock-sync":true,"src-clock-sync":true},{"dst-ts":16870463817297112529,"ip-ttl":255,"src-ts":16870463817293934253,"seq-num":49,"dst-clock-err":1.00583e-06,"src-clock-err":1.00583e-06,"dst-clock-sync":true,"src-clock-sync":true},{"dst-ts":16870463817382968925,"ip-ttl":255,"src-ts":16870463817380228736,"seq-num":50,"dst-clock-err":1.00583e-06,"src-clock-err":1.00583e-06,"dst-clock-sync":true,"src-clock-sync":true},{"dst-ts":16870463817784127461,"ip-ttl":255,"src-ts":16870463817780751616,"seq-num":51,"dst-clock-err":1.00583e-06,"src-clock-err":1.00583e-06,"dst-clock-sync":true,"src-clock-sync":true},{"dst-ts":16870463818009110733,"ip-ttl":255,"src-ts":16870463818006336184,"seq-num":52,"dst-clock-err":1.00583e-06,"src-clock-err":1.00583e-06,"dst-clock-sync":true,"src-clock-sync":true},{"dst-ts":16870463818112155588,"ip-ttl":255,"src-ts":16870463818108444736,"seq-num":53,"dst-clock-err":1.00583e-06,"src-clock-err":1.00583e-06,"dst-clock-sync":true,"src-clock-sync":true},{"dst-ts":16870463818166014478,"ip-ttl":255,"src-ts":16870463818162153302,"seq-num":54,"dst-clock-err":1.00583e-06,"src-clock-err":1.00583e-06,"dst-clock-sync":true,"src-clock-sync":true},{"dst-ts":16870463818882268994,"ip-ttl":255,"src-ts":16870463818879116488,"seq-num":55,"dst-clock-err":1.00583e-06,"src-clock-err":1.00583e-06,"dst-clock-sync":true,"src-clock-sync":true},{"dst-ts":16870463818889712172,"ip-ttl":255,"src-ts":16870463818886508127,"seq-num":56,"dst-clock-err":1.00583e-06,"src-clock-err":1.00583e-06,"dst-clock-sync":true,"src-clock-sync":true},{"dst-ts":16870463818903310039,"ip-ttl":255,"src-ts":16870463818900385166,"seq-num":57,"dst-clock-err":1.00583e-06,"src-clock-err":1.00583e-06,"dst-clock-sync":true,"src-clock-sync":true},{"dst-ts":16870463818908562784,"ip-ttl":255,"src-ts":16870463818905844069,"seq-num":58,"dst-clock-err":1.00583e-06,"src-clock-err":1.00583e-06,"dst-clock-sync":true,"src-clock-sync":true},{"dst-ts":16870463820025967245,"ip-ttl":255,"src-ts":16870463820023304366,"seq-num":59,"dst-clock-err":1.00583e-06,"src-clock-err":1.00583e-06,"dst-clock-sync":true,"src-clock-sync":true}],"packets-lost":0,"packets-sent":60,"histogram-ttl":{"255":60},"max-clock-error":0.0,"packets-received":60,"histogram-latency":{"0.60":2,"0.62":2,"0.63":5,"0.64":1,"0.65":3,"0.67":6,"0.68":3,"0.69":3,"0.70":1,"0.71":5,"0.73":1,"0.74":1,"0.75":1,"0.76":1,"0.77":3,"0.79":3,"0.80":1,"0.82":4,"0.83":2,"0.84":3,"0.85":1,"0.86":1,"0.87":1,"0.88":3,"0.89":1,"0.90":1,"1.02":1},"packets-reordered":0,"packets-duplicated":0}
